{"ok":true,"sourceTab":"BAR MENU NK","headers":["Category","Item Name","Description","Mocktail","30Ml","330Ml","275Ml","Glass","Silver","Repesado","Anezo","Btl","Pitcher(1.5 Lit)","Bar Man Special"],"items":[{"Category":"Awg & Classic Botanical Mixology ","Item Name":"Breezer Twist","Description":"White Rum,Strawberry Crush,Lime Juice,Sugar Syrup Top Up With Breezers.","Mocktail":"","30Ml":"","330Ml":"","275Ml":"","Glass":"529","Silver":"","Repesado":"","Anezo":"","Btl":"","Pitcher(1.5 Lit)":"","Bar Man Special":"No"},{"Category":"Awg & Classic Botanical Mixology ","Item Name":"Mai Tai","Description":"White Rum,Coconut Milk,Orange Juice,Pineapple Juice,Ice.","Mocktail":"","30Ml":"","330Ml":"","275Ml":"","Glass":"399","Silver":"","Repesado":"","Anezo":"","Btl":"","Pitcher(1.5 Lit)":"","Bar Man Special":"No"},{"Category":"Awg & Classic Botanical Mixology ","Item Name":"Old Monk Punch                                                                                                        ","Description":"Rum, Pineapple Juice, Cardamom, Rosemerry, Sweet & Sour.","Mocktail":"","30Ml":"","330Ml":"","275Ml":"","Glass":"379","Silver":"","Repesado":"","Anezo":"","Btl":"","Pitcher(1.5 Lit)":"","Bar Man Special":"No"},{"Category":"Awg & Classic Botanical Mixology ","Item Name":"Classic Mojito","Description":"White Rum, Mint Leaves, Lime Wedges Topped With Soda","Mocktail":"","30Ml":"","330Ml":"","275Ml":"","Glass":"349","Silver":"","Repesado":"","Anezo":"","Btl":"","Pitcher(1.5 Lit)":"","Bar Man Special":"No"},{"Category":"Awg & Classic Botanical Mixology ","Item Name":"Classic Pinacolada","Description":"Pineapple Juice, Coconut Cream With White Rum","Mocktail":"","30Ml":"","330Ml":"","275Ml":"","Glass":"349","Silver":"","Repesado":"","Anezo":"","Btl":"","Pitcher(1.5 Lit)":"","Bar Man Special":"No"},{"Category":"Awg & Classic Botanical Mixology ","Item Name":"Tom & Jerry","Description":"White Rum,Egg,Sugar Syrup,Brandy,Milk.","Mocktail":"","30Ml":"","330Ml":"","275Ml":"","Glass":"379","Silver":"","Repesado":"","Anezo":"","Btl":"","Pitcher(1.5 Lit)":"","Bar Man Special":"No"},{"Category":"Awg & Classic Botanical Mixology ","Item Name":"Sky Blue Colada","Description":"White Rum, Pineapple Juice, Blue Curacao Syrup,Coco Syrup,Fresh Cream.","Mocktail":"","30Ml":"","330Ml":"","275Ml":"","Glass":"379","Silver":"","Repesado":"","Anezo":"","Btl":"","Pitcher(1.5 Lit)":"","Bar Man Special":"No"},{"Category":"Awg & Classic Botanical Mixology ","Item Name":"Daiquiri ","Description":"White Rum, Lime Juice & Sugar Syrup","Mocktail":"","30Ml":"","330Ml":"","275Ml":"","Glass":"349","Silver":"","Repesado":"","Anezo":"","Btl":"","Pitcher(1.5 Lit)":"","Bar Man Special":"No"},{"Category":"Awg & Classic Botanical Mixology ","Item Name":"Pain Killer","Description":"White Rum,Coconut Milk,Orange Juice,Pineapple Juice,Ice.","Mocktail":"","30Ml":"","330Ml":"","275Ml":"","Glass":"349","Silver":"","Repesado":"","Anezo":"","Btl":"","Pitcher(1.5 Lit)":"","Bar Man Special":"No"},{"Category":"Awg & Classic Botanical Mixology ","Item Name":"Cuba Libra                                                                                                        ","Description":"White Rum, Cola & Fresh Lime & Mint.","Mocktail":"","30Ml":"","330Ml":"","275Ml":"","Glass":"329","Silver":"","Repesado":"","Anezo":"","Btl":"","Pitcher(1.5 Lit)":"","Bar Man Special":"No"},{"Category":"Awg & Classic Botanical Mixology ","Item Name":"Spicy Chilli Beer","Description":"Vodka,Larger Beer,Worcestershire Sauce,Tbasco,Green Chilli.","Mocktail":"","30Ml":"","330Ml":"","275Ml":"","Glass":"529","Silver":"","Repesado":"","Anezo":"","Btl":"","Pitcher(1.5 Lit)":"","Bar Man Special":"No"},{"Category":"Awg & Classic Botanical Mixology ","Item Name":"Sex On The Beach","Description":"Vodka, Orange Juice, Cranberry Juice & Peach Syrup","Mocktail":"","30Ml":"","330Ml":"","275Ml":"","Glass":"379","Silver":"","Repesado":"","Anezo":"","Btl":"","Pitcher(1.5 Lit)":"","Bar Man Special":"No"},{"Category":"Awg & Classic Botanical Mixology ","Item Name":"Classic Guava Marry","Description":"Vodka, Lime, Tobasco, Worcestershire Mixed With Guava Juice","Mocktail":"","30Ml":"","330Ml":"","275Ml":"","Glass":"379","Silver":"","Repesado":"","Anezo":"","Btl":"","Pitcher(1.5 Lit)":"","Bar Man Special":"No"},{"Category":"Awg & Classic Botanical Mixology ","Item Name":"Chocotini                                                                                     ","Description":"Vodka,Chocolate Syrup,Simple Syrup,Fresh Cream.","Mocktail":"","30Ml":"","330Ml":"","275Ml":"","Glass":"379","Silver":"","Repesado":"","Anezo":"","Btl":"","Pitcher(1.5 Lit)":"","Bar Man Special":"No"},{"Category":"Awg & Classic Botanical Mixology ","Item Name":"Passion Star Martini","Description":"Vodka, Orange Juice & Peach Syrup","Mocktail":"","30Ml":"","330Ml":"","275Ml":"","Glass":"349","Silver":"","Repesado":"","Anezo":"","Btl":"","Pitcher(1.5 Lit)":"","Bar Man Special":"No"},{"Category":"Awg & Classic Botanical Mixology ","Item Name":"Poison Love","Description":"Vodka, Orange Juice,Lime Juice","Mocktail":"","30Ml":"","330Ml":"","275Ml":"","Glass":"349","Silver":"","Repesado":"","Anezo":"","Btl":"","Pitcher(1.5 Lit)":"","Bar Man Special":"No"},{"Category":"Awg & Classic Botanical Mixology ","Item Name":"Cosmopolitan  ","Description":"Vodka, Cranberry Juice, Cointreau, Lime Juice","Mocktail":"","30Ml":"","330Ml":"","275Ml":"","Glass":"329","Silver":"","Repesado":"","Anezo":"","Btl":"","Pitcher(1.5 Lit)":"","Bar Man Special":"No"},{"Category":"Awg & Classic Botanical Mixology ","Item Name":"Classic Blue Lagoon","Description":"Vodka, Blue Curacao & Soda","Mocktail":"","30Ml":"","330Ml":"","275Ml":"","Glass":"329","Silver":"","Repesado":"","Anezo":"","Btl":"","Pitcher(1.5 Lit)":"","Bar Man Special":"No"},{"Category":"Awg & Classic Botanical Mixology ","Item Name":"New York Sour","Description":"Bourbon Whiskey,Lemon, Sugar Syrup, Egg(Optional), Top Up With Red Wine.","Mocktail":"","30Ml":"","330Ml":"","275Ml":"","Glass":"529","Silver":"","Repesado":"","Anezo":"","Btl":"","Pitcher(1.5 Lit)":"","Bar Man Special":"No"},{"Category":"Awg & Classic Botanical Mixology ","Item Name":"Whiskey Sour","Description":"Bourbon Whiskey,Sugar Syrup,Lemon,Egg(Optional),Angostura Bitters,Ice.","Mocktail":"","30Ml":"","330Ml":"","275Ml":"","Glass":"479","Silver":"","Repesado":"","Anezo":"","Btl":"","Pitcher(1.5 Lit)":"","Bar Man Special":"No"},{"Category":"Awg & Classic Botanical Mixology ","Item Name":"Old Fashioned","Description":"Bourbon Whiskey,Angostura Bitters,Orange Bitters,Water,Ice","Mocktail":"","30Ml":"","330Ml":"","275Ml":"","Glass":"499","Silver":"","Repesado":"","Anezo":"","Btl":"","Pitcher(1.5 Lit)":"","Bar Man Special":"No"},{"Category":"Awg & Classic Botanical Mixology ","Item Name":"Mint Julep ","Description":"Bourbon Whiskey, Simple Syrup, Mint With Crushed Ice","Mocktail":"","30Ml":"","330Ml":"","275Ml":"","Glass":"449","Silver":"","Repesado":"","Anezo":"","Btl":"","Pitcher(1.5 Lit)":"","Bar Man Special":"No"},{"Category":"Awg & Classic Botanical Mixology ","Item Name":"Hot Toddy","Description":"Whiskey,Honey,Lemon,Water.","Mocktail":"","30Ml":"","330Ml":"","275Ml":"","Glass":"399","Silver":"","Repesado":"","Anezo":"","Btl":"","Pitcher(1.5 Lit)":"","Bar Man Special":"No"},{"Category":"Awg & Classic Botanical Mixology ","Item Name":"Orange Julep","Description":"Whiskey, Fresh Orange,Simple Syrup, Mint With Crushed Ice","Mocktail":"","30Ml":"","330Ml":"","275Ml":"","Glass":"399","Silver":"","Repesado":"","Anezo":"","Btl":"","Pitcher(1.5 Lit)":"","Bar Man Special":"No"},{"Category":"Awg & Classic Botanical Mixology ","Item Name":"Let'S Detox","Description":"Gin,Watermelon Juice,Fresh Cucumber,Mint Leaves,Lime Juice & Symple Syrup.","Mocktail":"","30Ml":"","330Ml":"","275Ml":"","Glass":"449","Silver":"","Repesado":"","Anezo":"","Btl":"","Pitcher(1.5 Lit)":"","Bar Man Special":"No"},{"Category":"Awg & Classic Botanical Mixology ","Item Name":"Awgtini  (Martini)","Description":"Gin , Dry Vermouth, Olive","Mocktail":"","30Ml":"","330Ml":"","275Ml":"","Glass":"469","Silver":"","Repesado":"","Anezo":"","Btl":"","Pitcher(1.5 Lit)":"","Bar Man Special":"Yes"},{"Category":"Awg & Classic Botanical Mixology ","Item Name":"Chilli Basil Martini","Description":"Gin,Fresh Basil Leaves,Lime Juice,Sugar Syrup,Green Chilli.","Mocktail":"","30Ml":"","330Ml":"","275Ml":"","Glass":"399","Silver":"","Repesado":"","Anezo":"","Btl":"","Pitcher(1.5 Lit)":"","Bar Man Special":"No"},{"Category":"Awg & Classic Botanical Mixology ","Item Name":"White                                                                                                                     ","Description":"Gin, Triple Sec,Lime Juice & Sugar Syrup.","Mocktail":"","30Ml":"","330Ml":"","275Ml":"","Glass":"399","Silver":"","Repesado":"","Anezo":"","Btl":"","Pitcher(1.5 Lit)":"","Bar Man Special":"No"},{"Category":"Awg & Classic Botanical Mixology ","Item Name":"Pink Lady                                                                                                                       ","Description":"Gin, Triple Sec,Lime Juice & Sugar Syrup.","Mocktail":"","30Ml":"","330Ml":"","275Ml":"","Glass":"399","Silver":"","Repesado":"","Anezo":"","Btl":"","Pitcher(1.5 Lit)":"","Bar Man Special":"No"},{"Category":"Awg & Classic Botanical Mixology ","Item Name":"Gimlet","Description":"Gin, Lime Juice, Sugar Syrup","Mocktail":"","30Ml":"","330Ml":"","275Ml":"","Glass":"349","Silver":"","Repesado":"","Anezo":"","Btl":"","Pitcher(1.5 Lit)":"","Bar Man Special":"No"},{"Category":"Awg & Classic Botanical Mixology ","Item Name":"Green Maxican","Description":"Tequila,Midori,Lemon,Sugar Syrup,Ice.","Mocktail":"","30Ml":"","330Ml":"","275Ml":"","Glass":"599","Silver":"","Repesado":"","Anezo":"","Btl":"","Pitcher(1.5 Lit)":"","Bar Man Special":"No"},{"Category":"Awg & Classic Botanical Mixology ","Item Name":"Tequila Sunrise","Description":"Tequila, Orange Juice, Grenadine","Mocktail":"","30Ml":"","330Ml":"","275Ml":"","Glass":"499","Silver":"","Repesado":"","Anezo":"","Btl":"","Pitcher(1.5 Lit)":"","Bar Man Special":"No"},{"Category":"Awg & Classic Botanical Mixology ","Item Name":"Margarita","Description":"Tequila, Cointreau, Lime Juice","Mocktail":"","30Ml":"","330Ml":"","275Ml":"","Glass":"499","Silver":"","Repesado":"","Anezo":"","Btl":"","Pitcher(1.5 Lit)":"","Bar Man Special":"No"},{"Category":"Bull Base Cocktail","Item Name":"Bull Frog","Description":"Five Spirits Mixed With Red Bull And Tonic With Crushed Ice","Mocktail":"","30Ml":"","330Ml":"","275Ml":"","Glass":"699","Silver":"","Repesado":"","Anezo":"","Btl":"","Pitcher(1.5 Lit)":"","Bar Man Special":"No"},{"Category":"Bull Base Cocktail","Item Name":"Flying Bull","Description":"White & Dark Rum, Orange Juice & Red Bull","Mocktail":"","30Ml":"","330Ml":"","275Ml":"","Glass":"529","Silver":"","Repesado":"","Anezo":"","Btl":"","Pitcher(1.5 Lit)":"","Bar Man Special":"No"},{"Category":"Bull Base Cocktail","Item Name":"Bull Exotica","Description":"Vodka, Cranberry Juice, Peach Syrup & Red Bull","Mocktail":"","30Ml":"","330Ml":"","275Ml":"","Glass":"529","Silver":"","Repesado":"","Anezo":"","Btl":"","Pitcher(1.5 Lit)":"","Bar Man Special":"No"},{"Category":"Special Modern Mixology ","Item Name":"Drunk Maghai Paan","Description":"Vodka, Paan Syrup, Fresh Cream, Fresh Mint","Mocktail":"","30Ml":"","330Ml":"","275Ml":"","Glass":"499","Silver":"","Repesado":"","Anezo":"","Btl":"","Pitcher(1.5 Lit)":"","Bar Man Special":"No"},{"Category":"Special Modern Mixology ","Item Name":"Sunset Melon","Description":"Vodka,Fresh Watermelon,Lime Wedges,Fresh Mint,Pineapple Juice,Sprite.","Mocktail":"","30Ml":"","330Ml":"","275Ml":"","Glass":"499","Silver":"","Repesado":"","Anezo":"","Btl":"","Pitcher(1.5 Lit)":"","Bar Man Special":"No"},{"Category":"Special Modern Mixology ","Item Name":"The Awg Punch","Description":"Fresh Fruit, Vodka, Rum, Tequila, Mix Fruit Juice","Mocktail":"","30Ml":"","330Ml":"","275Ml":"","Glass":"499","Silver":"","Repesado":"","Anezo":"","Btl":"","Pitcher(1.5 Lit)":"","Bar Man Special":"No"},{"Category":"Special Modern Mixology ","Item Name":"Cranberry Kiss ","Description":"Cranberry Juice, Vodka, Lime","Mocktail":"","30Ml":"","330Ml":"","275Ml":"","Glass":"499","Silver":"","Repesado":"","Anezo":"","Btl":"","Pitcher(1.5 Lit)":"","Bar Man Special":"No"},{"Category":"Special Modern Mixology ","Item Name":"Lost In Litchi","Description":"Gin,Litchi Juice,Cranberry Juice,Elderflower Syrup,Lime Juice","Mocktail":"","30Ml":"","330Ml":"","275Ml":"","Glass":"499","Silver":"","Repesado":"","Anezo":"","Btl":"","Pitcher(1.5 Lit)":"","Bar Man Special":"No"},{"Category":"Special Modern Mixology ","Item Name":"Trust In Me","Description":"Whiskey,Mulled Wine,Egg White,Lime Juice","Mocktail":"","30Ml":"","330Ml":"","275Ml":"","Glass":"499","Silver":"","Repesado":"","Anezo":"","Btl":"","Pitcher(1.5 Lit)":"","Bar Man Special":"No"},{"Category":"Shots","Item Name":"Jager Bomb","Description":"Jagermeister And Red Bull","Mocktail":"","30Ml":"","330Ml":"","275Ml":"","Glass":"579","Silver":"","Repesado":"","Anezo":"","Btl":"","Pitcher(1.5 Lit)":"","Bar Man Special":"No"},{"Category":"Shots","Item Name":"Bacadi  Mango Chilli Shot","Description":"","Mocktail":"","30Ml":"","330Ml":"","275Ml":"","Glass":"299","Silver":"","Repesado":"","Anezo":"","Btl":"","Pitcher(1.5 Lit)":"","Bar Man Special":"No"},{"Category":"Shots","Item Name":"B52","Description":"Kahlua, Baileys, Triple Sec","Mocktail":"","30Ml":"","330Ml":"","275Ml":"","Glass":"579","Silver":"","Repesado":"","Anezo":"","Btl":"","Pitcher(1.5 Lit)":"","Bar Man Special":"No"},{"Category":"Shots","Item Name":"Bmw","Description":"Baileys, Malibu, Whiskey","Mocktail":"","30Ml":"","330Ml":"","275Ml":"","Glass":"579","Silver":"","Repesado":"","Anezo":"","Btl":"","Pitcher(1.5 Lit)":"","Bar Man Special":"No"},{"Category":"Shots","Item Name":"Jack Sparrow","Description":"Jd & Sambuca","Mocktail":"","30Ml":"","330Ml":"","275Ml":"","Glass":"549","Silver":"","Repesado":"","Anezo":"","Btl":"","Pitcher(1.5 Lit)":"","Bar Man Special":"No"},{"Category":"Shots","Item Name":"Jack Sparrow","Description":"Jd & Sambuca","Mocktail":"","30Ml":"","330Ml":"","275Ml":"","Glass":"549","Silver":"","Repesado":"","Anezo":"","Btl":"","Pitcher(1.5 Lit)":"","Bar Man Special":"No"},{"Category":"Shots","Item Name":"Irish Frog","Description":"Baileys, Midori.","Mocktail":"","30Ml":"","330Ml":"","275Ml":"","Glass":"549","Silver":"","Repesado":"","Anezo":"","Btl":"","Pitcher(1.5 Lit)":"","Bar Man Special":"No"},{"Category":"Shots","Item Name":"Drunk Melon","Description":"Sambuca,Gin,Midori,Lemon.","Mocktail":"","30Ml":"","330Ml":"","275Ml":"","Glass":"529","Silver":"","Repesado":"","Anezo":"","Btl":"","Pitcher(1.5 Lit)":"","Bar Man Special":"No"},{"Category":"Shots","Item Name":"Passion Blondy","Description":"Bacardi, Cointreau, Lime Juice","Mocktail":"","30Ml":"","330Ml":"","275Ml":"","Glass":"529","Silver":"","Repesado":"","Anezo":"","Btl":"","Pitcher(1.5 Lit)":"","Bar Man Special":"No"},{"Category":"Shots","Item Name":"Fighting Bull","Description":"Grenadine, Vodka, Red Bull","Mocktail":"","30Ml":"","330Ml":"","275Ml":"","Glass":"429","Silver":"","Repesado":"","Anezo":"","Btl":"","Pitcher(1.5 Lit)":"","Bar Man Special":"No"},{"Category":"Shots","Item Name":"Kamikazi","Description":"Vodka, Cointreau, Lime Juice","Mocktail":"","30Ml":"","330Ml":"","275Ml":"","Glass":"429","Silver":"","Repesado":"","Anezo":"","Btl":"","Pitcher(1.5 Lit)":"","Bar Man Special":"No"},{"Category":"Sangria                                                 ","Item Name":"White Wine Sangria                                                                                    ","Description":"White Wine,Fresh Orange & Apple,Brandy,Sugar,Soda","Mocktail":"","30Ml":"","330Ml":"","275Ml":"","Glass":"429","Silver":"","Repesado":"","Anezo":"","Btl":"","Pitcher(1.5 Lit)":"2999","Bar Man Special":"No"},{"Category":"Sangria                                                 ","Item Name":"Red Wine Sangria                                                                                         ","Description":"Red Wine,Fresh Orange & Apple,Brandy,Sugar,Soda","Mocktail":"","30Ml":"","330Ml":"","275Ml":"","Glass":"429","Silver":"","Repesado":"","Anezo":"","Btl":"","Pitcher(1.5 Lit)":"2999","Bar Man Special":"No"},{"Category":"Liit Long Glass","Item Name":"Awg Liit","Description":"Five White Spirits, Peach Syrup Topped With Redwine","Mocktail":"","30Ml":"","330Ml":"","275Ml":"","Glass":"729","Silver":"","Repesado":"","Anezo":"","Btl":"","Pitcher(1.5 Lit)":"","Bar Man Special":"No"},{"Category":"Liit Long Glass","Item Name":"Beer Liit","Description":"Five White Spirits Topped With Beer, Choice Of Flavour","Mocktail":"","30Ml":"","330Ml":"","275Ml":"","Glass":"699","Silver":"","Repesado":"","Anezo":"","Btl":"","Pitcher(1.5 Lit)":"","Bar Man Special":"No"},{"Category":"Liit Long Glass","Item Name":"Boom Boom Liit","Description":"Vodka, Tequilla, Rum Topped With Red Bull And Crushed Ice","Mocktail":"","30Ml":"","330Ml":"","275Ml":"","Glass":"699","Silver":"","Repesado":"","Anezo":"","Btl":"","Pitcher(1.5 Lit)":"","Bar Man Special":"No"},{"Category":"Liit Long Glass","Item Name":"Cranberry Liit","Description":"Five Spirits Topped With Grenadine And Cranberry Juice","Mocktail":"","30Ml":"","330Ml":"","275Ml":"","Glass":"649","Silver":"","Repesado":"","Anezo":"","Btl":"","Pitcher(1.5 Lit)":"","Bar Man Special":"No"},{"Category":"Liit Long Glass","Item Name":"Classic Liit","Description":"Five Spirits Mixed With Cola","Mocktail":"","30Ml":"","330Ml":"","275Ml":"","Glass":"649","Silver":"","Repesado":"","Anezo":"","Btl":"","Pitcher(1.5 Lit)":"","Bar Man Special":"No"},{"Category":"Scotch Whisky","Item Name":"Dewar'S 15 Yo","Description":"","Mocktail":"","30Ml":"549","330Ml":"","275Ml":"","Glass":"","Silver":"","Repesado":"","Anezo":"","Btl":"","Pitcher(1.5 Lit)":"","Bar Man Special":"No"},{"Category":"Scotch Whisky","Item Name":"Dewar'S 12 Yo","Description":"","Mocktail":"","30Ml":"459","330Ml":"","275Ml":"","Glass":"","Silver":"","Repesado":"","Anezo":"","Btl":"","Pitcher(1.5 Lit)":"","Bar Man Special":"No"},{"Category":"Scotch Whisky","Item Name":"Dewar'S Portuguese Smooth","Description":"","Mocktail":"","30Ml":"359","330Ml":"","275Ml":"","Glass":"","Silver":"","Repesado":"","Anezo":"","Btl":"","Pitcher(1.5 Lit)":"","Bar Man Special":"No"},{"Category":"Scotch Whisky","Item Name":"Dewar'S White Label","Description":"","Mocktail":"","30Ml":"299","330Ml":"","275Ml":"","Glass":"","Silver":"","Repesado":"","Anezo":"","Btl":"","Pitcher(1.5 Lit)":"","Bar Man Special":"No"},{"Category":"Scotch Whisky","Item Name":"Johnnie Walker Blue Label","Description":"","Mocktail":"","30Ml":"2299","330Ml":"","275Ml":"","Glass":"","Silver":"","Repesado":"","Anezo":"","Btl":"","Pitcher(1.5 Lit)":"","Bar Man Special":"No"},{"Category":"Scotch Whisky","Item Name":"Royal Salute 21Yrs","Description":"","Mocktail":"","30Ml":"2299","330Ml":"","275Ml":"","Glass":"","Silver":"","Repesado":"","Anezo":"","Btl":"","Pitcher(1.5 Lit)":"","Bar Man Special":"No"},{"Category":"Scotch Whisky","Item Name":"Johnnie Walker Double Black ","Description":"","Mocktail":"","30Ml":"549","330Ml":"","275Ml":"","Glass":"","Silver":"","Repesado":"","Anezo":"","Btl":"","Pitcher(1.5 Lit)":"","Bar Man Special":"No"},{"Category":"Scotch Whisky","Item Name":"Monkey Shoulder","Description":"","Mocktail":"","30Ml":"549","330Ml":"","275Ml":"","Glass":"","Silver":"","Repesado":"","Anezo":"","Btl":"","Pitcher(1.5 Lit)":"","Bar Man Special":"No"},{"Category":"Scotch Whisky","Item Name":"Chivas Regal 12 Y.O.","Description":"","Mocktail":"","30Ml":"459","330Ml":"","275Ml":"","Glass":"","Silver":"","Repesado":"","Anezo":"","Btl":"","Pitcher(1.5 Lit)":"","Bar Man Special":"No"},{"Category":"Scotch Whisky","Item Name":"Johnnie Walker Black Label 12 Yrs.","Description":"","Mocktail":"","30Ml":"459","330Ml":"","275Ml":"","Glass":"","Silver":"","Repesado":"","Anezo":"","Btl":"","Pitcher(1.5 Lit)":"","Bar Man Special":"No"},{"Category":"Scotch Whisky","Item Name":"J & B","Description":"","Mocktail":"","30Ml":"329","330Ml":"","275Ml":"","Glass":"","Silver":"","Repesado":"","Anezo":"","Btl":"","Pitcher(1.5 Lit)":"","Bar Man Special":"No"},{"Category":"Scotch Whisky","Item Name":"Johnnie Walker Red Label","Description":"","Mocktail":"","30Ml":"299","330Ml":"","275Ml":"","Glass":"","Silver":"","Repesado":"","Anezo":"","Btl":"","Pitcher(1.5 Lit)":"","Bar Man Special":"No"},{"Category":"Single Malt","Item Name":"Laphroaig 10 Y.O.","Description":"","Mocktail":"","30Ml":"949","330Ml":"","275Ml":"","Glass":"","Silver":"","Repesado":"","Anezo":"","Btl":"","Pitcher(1.5 Lit)":"","Bar Man Special":"No"},{"Category":"Single Malt","Item Name":"Glenfiddich 12 Yrs. ","Description":"","Mocktail":"","30Ml":"729","330Ml":"","275Ml":"","Glass":"","Silver":"","Repesado":"","Anezo":"","Btl":"","Pitcher(1.5 Lit)":"","Bar Man Special":"No"},{"Category":"Single Malt","Item Name":"Talisker 10 Yrs.","Description":"","Mocktail":"","30Ml":"729","330Ml":"","275Ml":"","Glass":"","Silver":"","Repesado":"","Anezo":"","Btl":"","Pitcher(1.5 Lit)":"","Bar Man Special":"No"},{"Category":"Single Malt","Item Name":"Glenlivet 12 Yrs.","Description":"","Mocktail":"","30Ml":"729","330Ml":"","275Ml":"","Glass":"","Silver":"","Repesado":"","Anezo":"","Btl":"","Pitcher(1.5 Lit)":"","Bar Man Special":"No"},{"Category":"Single Malt","Item Name":"Glenmorangie. 10 Yrs.","Description":"","Mocktail":"","30Ml":"729","330Ml":"","275Ml":"","Glass":"","Silver":"","Repesado":"","Anezo":"","Btl":"","Pitcher(1.5 Lit)":"","Bar Man Special":"No"},{"Category":"Single Malt","Item Name":"Aberfeldy 12Yo","Description":"","Mocktail":"","30Ml":"800","330Ml":"","275Ml":"","Glass":"","Silver":"","Repesado":"","Anezo":"","Btl":"","Pitcher(1.5 Lit)":"","Bar Man Special":"No"},{"Category":"Single Malt","Item Name":"Amrut ","Description":"","Mocktail":"","30Ml":"529","330Ml":"","275Ml":"","Glass":"","Silver":"","Repesado":"","Anezo":"","Btl":"","Pitcher(1.5 Lit)":"","Bar Man Special":"No"},{"Category":"Bourbon / Irish Whisky","Item Name":"Jack Daniel'S Old No.07 ","Description":"","Mocktail":"","30Ml":"429","330Ml":"","275Ml":"","Glass":"","Silver":"","Repesado":"","Anezo":"","Btl":"","Pitcher(1.5 Lit)":"","Bar Man Special":"No"},{"Category":"Bourbon / Irish Whisky","Item Name":"Jack Daniel'S Old No.07  Honey ","Description":"","Mocktail":"","30Ml":"429","330Ml":"","275Ml":"","Glass":"","Silver":"","Repesado":"","Anezo":"","Btl":"","Pitcher(1.5 Lit)":"","Bar Man Special":"No"},{"Category":"Bourbon / Irish Whisky","Item Name":"Jack Daniel'S Old No.07  Fire","Description":"","Mocktail":"","30Ml":"429","330Ml":"","275Ml":"","Glass":"","Silver":"","Repesado":"","Anezo":"","Btl":"","Pitcher(1.5 Lit)":"","Bar Man Special":"No"},{"Category":"Bourbon / Irish Whisky","Item Name":"Jim Beam","Description":"","Mocktail":"","30Ml":"359","330Ml":"","275Ml":"","Glass":"","Silver":"","Repesado":"","Anezo":"","Btl":"","Pitcher(1.5 Lit)":"","Bar Man Special":"No"},{"Category":"Bourbon / Irish Whisky","Item Name":"Jameson ","Description":"","Mocktail":"","30Ml":"359","330Ml":"","275Ml":"","Glass":"","Silver":"","Repesado":"","Anezo":"","Btl":"","Pitcher(1.5 Lit)":"","Bar Man Special":"No"},{"Category":"Premium Whisky","Item Name":"Teachers 50                                                                    ","Description":"","Mocktail":"","30Ml":"379","330Ml":"","275Ml":"","Glass":"","Silver":"","Repesado":"","Anezo":"","Btl":"","Pitcher(1.5 Lit)":"","Bar Man Special":"No"},{"Category":"Premium Whisky","Item Name":"Black Dog Triple Gold","Description":"","Mocktail":"","30Ml":"369","330Ml":"","275Ml":"","Glass":"","Silver":"","Repesado":"","Anezo":"","Btl":"","Pitcher(1.5 Lit)":"","Bar Man Special":"No"},{"Category":"Premium Whisky","Item Name":"Teachers Highland Cream","Description":"","Mocktail":"","30Ml":"309","330Ml":"","275Ml":"","Glass":"","Silver":"","Repesado":"","Anezo":"","Btl":"","Pitcher(1.5 Lit)":"","Bar Man Special":"No"},{"Category":"Premium Whisky","Item Name":"Black & White","Description":"","Mocktail":"","30Ml":"299","330Ml":"","275Ml":"","Glass":"","Silver":"","Repesado":"","Anezo":"","Btl":"","Pitcher(1.5 Lit)":"","Bar Man Special":"No"},{"Category":"Premium Whisky","Item Name":"100 Pipers ","Description":"","Mocktail":"","30Ml":"299","330Ml":"","275Ml":"","Glass":"","Silver":"","Repesado":"","Anezo":"","Btl":"","Pitcher(1.5 Lit)":"","Bar Man Special":"No"},{"Category":"Premium Whisky","Item Name":"Vat 69","Description":"","Mocktail":"","30Ml":"299","330Ml":"","275Ml":"","Glass":"","Silver":"","Repesado":"","Anezo":"","Btl":"","Pitcher(1.5 Lit)":"","Bar Man Special":"No"},{"Category":"Premium Whisky","Item Name":"Ballentine’S Finest","Description":"","Mocktail":"","30Ml":"289","330Ml":"","275Ml":"","Glass":"","Silver":"","Repesado":"","Anezo":"","Btl":"","Pitcher(1.5 Lit)":"","Bar Man Special":"No"},{"Category":"Premium Whisky","Item Name":"Willam Lawson'S","Description":"","Mocktail":"","30Ml":"249","330Ml":"","275Ml":"","Glass":"","Silver":"","Repesado":"","Anezo":"","Btl":"","Pitcher(1.5 Lit)":"","Bar Man Special":"No"},{"Category":"Premium Whisky","Item Name":"The Glenwalk","Description":"","Mocktail":"","30Ml":"249","330Ml":"","275Ml":"","Glass":"","Silver":"","Repesado":"","Anezo":"","Btl":"","Pitcher(1.5 Lit)":"","Bar Man Special":"No"},{"Category":"Premium Whisky","Item Name":"Blenders Pride Reserved","Description":"","Mocktail":"","30Ml":"209","330Ml":"","275Ml":"","Glass":"","Silver":"","Repesado":"","Anezo":"","Btl":"","Pitcher(1.5 Lit)":"","Bar Man Special":"No"},{"Category":"Premium Whisky","Item Name":"Antiquity Blue","Description":"","Mocktail":"","30Ml":"209","330Ml":"","275Ml":"","Glass":"","Silver":"","Repesado":"","Anezo":"","Btl":"","Pitcher(1.5 Lit)":"","Bar Man Special":"No"},{"Category":"Premium Whisky","Item Name":"Signature ","Description":"","Mocktail":"","30Ml":"199","330Ml":"","275Ml":"","Glass":"","Silver":"","Repesado":"","Anezo":"","Btl":"","Pitcher(1.5 Lit)":"","Bar Man Special":"No"},{"Category":"Premium Whisky","Item Name":"Blenders Pride","Description":"","Mocktail":"","30Ml":"199","330Ml":"","275Ml":"","Glass":"","Silver":"","Repesado":"","Anezo":"","Btl":"","Pitcher(1.5 Lit)":"","Bar Man Special":"No"},{"Category":"Premium Whisky","Item Name":"Oaksmith Gold","Description":"","Mocktail":"","30Ml":"199","330Ml":"","275Ml":"","Glass":"","Silver":"","Repesado":"","Anezo":"","Btl":"","Pitcher(1.5 Lit)":"","Bar Man Special":"No"},{"Category":"Premium Whisky","Item Name":"Oaksmith Silver","Description":"","Mocktail":"","30Ml":"199","330Ml":"","275Ml":"","Glass":"","Silver":"","Repesado":"","Anezo":"","Btl":"","Pitcher(1.5 Lit)":"","Bar Man Special":"No"},{"Category":"Premium Whisky","Item Name":"Okan Glow","Description":"","Mocktail":"","30Ml":"159","330Ml":"","275Ml":"","Glass":"","Silver":"","Repesado":"","Anezo":"","Btl":"","Pitcher(1.5 Lit)":"","Bar Man Special":"No"},{"Category":"Imported Vodka","Item Name":"Grey Goose","Description":"","Mocktail":"","30Ml":"599","330Ml":"","275Ml":"","Glass":"","Silver":"","Repesado":"","Anezo":"","Btl":"","Pitcher(1.5 Lit)":"","Bar Man Special":"No"},{"Category":"Imported Vodka","Item Name":"Cîroc","Description":"","Mocktail":"","30Ml":"579","330Ml":"","275Ml":"","Glass":"","Silver":"","Repesado":"","Anezo":"","Btl":"","Pitcher(1.5 Lit)":"","Bar Man Special":"No"},{"Category":"Imported Vodka","Item Name":"Absolut ","Description":"","Mocktail":"","30Ml":"329","330Ml":"","275Ml":"","Glass":"","Silver":"","Repesado":"","Anezo":"","Btl":"","Pitcher(1.5 Lit)":"","Bar Man Special":"No"},{"Category":"Imported Vodka","Item Name":" Absolut Flavor","Description":"","Mocktail":"","30Ml":"329","330Ml":"","275Ml":"","Glass":"","Silver":"","Repesado":"","Anezo":"","Btl":"","Pitcher(1.5 Lit)":"","Bar Man Special":"No"},{"Category":"Domestic Vodka","Item Name":"Smirnoff ","Description":"","Mocktail":"","30Ml":"209","330Ml":"","275Ml":"","Glass":"","Silver":"","Repesado":"","Anezo":"","Btl":"","Pitcher(1.5 Lit)":"","Bar Man Special":"No"},{"Category":"Domestic Vodka","Item Name":" Smirnoff Flavor","Description":"","Mocktail":"","30Ml":"209","330Ml":"","275Ml":"","Glass":"","Silver":"","Repesado":"","Anezo":"","Btl":"","Pitcher(1.5 Lit)":"","Bar Man Special":"No"},{"Category":"Domestic Vodka","Item Name":"Magic Moment","Description":"","Mocktail":"","30Ml":"149","330Ml":"","275Ml":"","Glass":"","Silver":"","Repesado":"","Anezo":"","Btl":"","Pitcher(1.5 Lit)":"","Bar Man Special":"No"},{"Category":"Gin","Item Name":"Jaisalmer","Description":"","Mocktail":"","30Ml":"399","330Ml":"","275Ml":"","Glass":"","Silver":"","Repesado":"","Anezo":"","Btl":"","Pitcher(1.5 Lit)":"","Bar Man Special":"No"},{"Category":"Gin","Item Name":"Bombay Sapphire","Description":"","Mocktail":"","30Ml":"329","330Ml":"","275Ml":"","Glass":"","Silver":"","Repesado":"","Anezo":"","Btl":"","Pitcher(1.5 Lit)":"","Bar Man Special":"No"},{"Category":"Gin","Item Name":"Beefeater ","Description":"","Mocktail":"","30Ml":"299","330Ml":"","275Ml":"","Glass":"","Silver":"","Repesado":"","Anezo":"","Btl":"","Pitcher(1.5 Lit)":"","Bar Man Special":"No"},{"Category":"Gin","Item Name":"Blue Riband","Description":"","Mocktail":"","30Ml":"149","330Ml":"","275Ml":"","Glass":"","Silver":"","Repesado":"","Anezo":"","Btl":"","Pitcher(1.5 Lit)":"","Bar Man Special":"No"},{"Category":"Liquer","Item Name":"Malibu","Description":"","Mocktail":"","30Ml":"399","330Ml":"","275Ml":"","Glass":"","Silver":"","Repesado":"","Anezo":"","Btl":"","Pitcher(1.5 Lit)":"","Bar Man Special":"No"},{"Category":"Domestic Rum","Item Name":"Bacardi White Rum ","Description":"","Mocktail":"","30Ml":"159","330Ml":"","275Ml":"","Glass":"","Silver":"","Repesado":"","Anezo":"","Btl":"","Pitcher(1.5 Lit)":"","Bar Man Special":"No"},{"Category":"Domestic Rum","Item Name":"Bacardi  Black Rum","Description":"","Mocktail":"","30Ml":"159","330Ml":"","275Ml":"","Glass":"","Silver":"","Repesado":"","Anezo":"","Btl":"","Pitcher(1.5 Lit)":"","Bar Man Special":"No"},{"Category":"Domestic Rum","Item Name":"Old Monk Coffee","Description":"","Mocktail":"","30Ml":"209","330Ml":"","275Ml":"","Glass":"","Silver":"","Repesado":"","Anezo":"","Btl":"","Pitcher(1.5 Lit)":"","Bar Man Special":"No"},{"Category":"Domestic Rum","Item Name":"Captain Morgan","Description":"","Mocktail":"","30Ml":"159","330Ml":"","275Ml":"","Glass":"","Silver":"","Repesado":"","Anezo":"","Btl":"","Pitcher(1.5 Lit)":"","Bar Man Special":"No"},{"Category":"Domestic Rum","Item Name":" Old Monk White","Description":"","Mocktail":"","30Ml":"129","330Ml":"","275Ml":"","Glass":"","Silver":"","Repesado":"","Anezo":"","Btl":"","Pitcher(1.5 Lit)":"","Bar Man Special":"No"},{"Category":"Domestic Rum","Item Name":"Old Monk Regular ","Description":"","Mocktail":"","30Ml":"129","330Ml":"","275Ml":"","Glass":"","Silver":"","Repesado":"","Anezo":"","Btl":"","Pitcher(1.5 Lit)":"","Bar Man Special":"No"},{"Category":"Brandy ","Item Name":"Hennessy V.S.","Description":"","Mocktail":"","30Ml":"599","330Ml":"","275Ml":"","Glass":"","Silver":"","Repesado":"","Anezo":"","Btl":"","Pitcher(1.5 Lit)":"","Bar Man Special":"No"},{"Category":"Tequila","Item Name":"Patron ","Description":"","Mocktail":"","30Ml":"","330Ml":"","275Ml":"","Glass":"","Silver":"949","Repesado":"1099","Anezo":"949","Btl":"","Pitcher(1.5 Lit)":"","Bar Man Special":"No"},{"Category":"Tequila","Item Name":"Tequila Camino Gold ","Description":"","Mocktail":"","30Ml":"409","330Ml":"","275Ml":"","Glass":"","Silver":"","Repesado":"","Anezo":"","Btl":"","Pitcher(1.5 Lit)":"","Bar Man Special":"No"},{"Category":"Tequila","Item Name":"Tequila Camino Silver","Description":"","Mocktail":"","30Ml":"409","330Ml":"","275Ml":"","Glass":"","Silver":"","Repesado":"","Anezo":"","Btl":"","Pitcher(1.5 Lit)":"","Bar Man Special":"No"},{"Category":"Tequila","Item Name":"Don Angel","Description":"","Mocktail":"","30Ml":"379","330Ml":"","275Ml":"","Glass":"","Silver":"","Repesado":"","Anezo":"","Btl":"","Pitcher(1.5 Lit)":"","Bar Man Special":"No"},{"Category":"Liqueurs","Item Name":"Triple Sec ","Description":"","Mocktail":"","30Ml":"499","330Ml":"","275Ml":"","Glass":"","Silver":"","Repesado":"","Anezo":"","Btl":"","Pitcher(1.5 Lit)":"","Bar Man Special":"No"},{"Category":"Liqueurs","Item Name":"Cointreau    ","Description":"","Mocktail":"","30Ml":"499","330Ml":"","275Ml":"","Glass":"","Silver":"","Repesado":"","Anezo":"","Btl":"","Pitcher(1.5 Lit)":"","Bar Man Special":"No"},{"Category":"Liqueurs","Item Name":"Jagermeister","Description":"","Mocktail":"","30Ml":"499","330Ml":"","275Ml":"","Glass":"","Silver":"","Repesado":"","Anezo":"","Btl":"","Pitcher(1.5 Lit)":"","Bar Man Special":"No"},{"Category":"Liqueurs","Item Name":"Baileys                                                                         ","Description":"","Mocktail":"","30Ml":"399","330Ml":"","275Ml":"","Glass":"","Silver":"","Repesado":"","Anezo":"","Btl":"","Pitcher(1.5 Lit)":"","Bar Man Special":"No"},{"Category":"Liqueurs","Item Name":"Sambuca","Description":"","Mocktail":"","30Ml":"379","330Ml":"","275Ml":"","Glass":"","Silver":"","Repesado":"","Anezo":"","Btl":"","Pitcher(1.5 Lit)":"","Bar Man Special":"No"},{"Category":"Liqueurs","Item Name":"Kahlua","Description":"","Mocktail":"","30Ml":"379","330Ml":"","275Ml":"","Glass":"","Silver":"","Repesado":"","Anezo":"","Btl":"","Pitcher(1.5 Lit)":"","Bar Man Special":"No"},{"Category":"Liqueurs","Item Name":"Midori","Description":"","Mocktail":"","30Ml":"379","330Ml":"","275Ml":"","Glass":"","Silver":"","Repesado":"","Anezo":"","Btl":"","Pitcher(1.5 Lit)":"","Bar Man Special":"No"},{"Category":"Liqueurs","Item Name":"Martini","Description":"","Mocktail":"","30Ml":"379","330Ml":"","275Ml":"","Glass":"","Silver":"","Repesado":"","Anezo":"","Btl":"","Pitcher(1.5 Lit)":"","Bar Man Special":"No"},{"Category":"Beer'S","Item Name":"Hoegaarden","Description":"","Mocktail":"","30Ml":"","330Ml":"409","275Ml":"","Glass":"","Silver":"","Repesado":"","Anezo":"","Btl":"","Pitcher(1.5 Lit)":"","Bar Man Special":"No"},{"Category":"Beer'S","Item Name":"Corona","Description":"","Mocktail":"","30Ml":"","330Ml":"409","275Ml":"","Glass":"","Silver":"","Repesado":"","Anezo":"","Btl":"","Pitcher(1.5 Lit)":"","Bar Man Special":"No"},{"Category":"Beer'S","Item Name":"Budweiser Magnum","Description":"","Mocktail":"","30Ml":"","330Ml":"349","275Ml":"","Glass":"","Silver":"","Repesado":"","Anezo":"","Btl":"","Pitcher(1.5 Lit)":"","Bar Man Special":"No"},{"Category":"Beer'S","Item Name":"Budweiser Premium","Description":"","Mocktail":"","30Ml":"","330Ml":"329","275Ml":"","Glass":"","Silver":"","Repesado":"","Anezo":"","Btl":"","Pitcher(1.5 Lit)":"","Bar Man Special":"No"},{"Category":"Beer'S","Item Name":"Kingfisher Ultra","Description":"","Mocktail":"","30Ml":"","330Ml":"329","275Ml":"","Glass":"","Silver":"","Repesado":"","Anezo":"","Btl":"","Pitcher(1.5 Lit)":"","Bar Man Special":"No"},{"Category":"Beer'S","Item Name":"Heineken ","Description":"","Mocktail":"","30Ml":"","330Ml":"329","275Ml":"","Glass":"","Silver":"","Repesado":"","Anezo":"","Btl":"","Pitcher(1.5 Lit)":"","Bar Man Special":"No"},{"Category":"Beer'S","Item Name":"Heineken  Silver","Description":"","Mocktail":"","30Ml":"","330Ml":"329","275Ml":"","Glass":"","Silver":"","Repesado":"","Anezo":"","Btl":"","Pitcher(1.5 Lit)":"","Bar Man Special":"No"},{"Category":"Beer'S","Item Name":"Carlsberg Elephent ","Description":"","Mocktail":"","30Ml":"","330Ml":"329","275Ml":"","Glass":"","Silver":"","Repesado":"","Anezo":"","Btl":"","Pitcher(1.5 Lit)":"","Bar Man Special":"No"},{"Category":"Beer'S","Item Name":"Carlsberg Smooth","Description":"","Mocktail":"","30Ml":"","330Ml":"289","275Ml":"","Glass":"","Silver":"","Repesado":"","Anezo":"","Btl":"","Pitcher(1.5 Lit)":"","Bar Man Special":"No"},{"Category":"Beer'S","Item Name":"Tuborg Strong","Description":"","Mocktail":"","30Ml":"","330Ml":"279","275Ml":"","Glass":"","Silver":"","Repesado":"","Anezo":"","Btl":"","Pitcher(1.5 Lit)":"","Bar Man Special":"No"},{"Category":"Beer'S","Item Name":"Kingfisher Premium","Description":"","Mocktail":"","30Ml":"","330Ml":"269","275Ml":"","Glass":"","Silver":"","Repesado":"","Anezo":"","Btl":"","Pitcher(1.5 Lit)":"","Bar Man Special":"No"},{"Category":"Breezers                ","Item Name":"Cranberry ","Description":"","Mocktail":"","30Ml":"","330Ml":"","275Ml":"299","Glass":"","Silver":"","Repesado":"","Anezo":"","Btl":"","Pitcher(1.5 Lit)":"","Bar Man Special":"No"},{"Category":"Breezers                ","Item Name":"Jamaican Passion","Description":"","Mocktail":"","30Ml":"","330Ml":"","275Ml":"299","Glass":"","Silver":"","Repesado":"","Anezo":"","Btl":"","Pitcher(1.5 Lit)":"","Bar Man Special":"No"},{"Category":"Sparkling Wine","Item Name":"Sula Brut","Description":"","Mocktail":"","30Ml":"","330Ml":"","275Ml":"","Glass":"","Silver":"","Repesado":"","Anezo":"","Btl":"2599","Pitcher(1.5 Lit)":"","Bar Man Special":"No"},{"Category":"Sparkling Wine","Item Name":"Sula Seco","Description":"","Mocktail":"","30Ml":"","330Ml":"","275Ml":"","Glass":"","Silver":"","Repesado":"","Anezo":"","Btl":"1699","Pitcher(1.5 Lit)":"","Bar Man Special":"No"},{"Category":"Red Wine","Item Name":"Jacob Creak Merlot ","Description":"","Mocktail":"","30Ml":"","330Ml":"","275Ml":"","Glass":"","Silver":"","Repesado":"","Anezo":"","Btl":"2699","Pitcher(1.5 Lit)":"","Bar Man Special":"No"},{"Category":"Red Wine","Item Name":" Shiraz","Description":"","Mocktail":"","30Ml":"","330Ml":"","275Ml":"","Glass":"","Silver":"","Repesado":"","Anezo":"","Btl":"2699","Pitcher(1.5 Lit)":"","Bar Man Special":"No"},{"Category":"Red Wine","Item Name":"Sula Dindori ","Description":"","Mocktail":"","30Ml":"","330Ml":"","275Ml":"","Glass":"479","Silver":"","Repesado":"","Anezo":"","Btl":"1999","Pitcher(1.5 Lit)":"","Bar Man Special":"No"},{"Category":"Red Wine","Item Name":"Sula Cabernet Shiraz ","Description":"","Mocktail":"","30Ml":"","330Ml":"","275Ml":"","Glass":"399","Silver":"","Repesado":"","Anezo":"","Btl":"1899","Pitcher(1.5 Lit)":"","Bar Man Special":"No"},{"Category":"Red Wine","Item Name":"Sula  Satroi","Description":"","Mocktail":"","30Ml":"","330Ml":"","275Ml":"","Glass":"399","Silver":"","Repesado":"","Anezo":"","Btl":"1899","Pitcher(1.5 Lit)":"","Bar Man Special":"No"},{"Category":"Red Wine","Item Name":"Fratelli Classic Merlot ","Description":"","Mocktail":"","30Ml":"","330Ml":"","275Ml":"","Glass":"349","Silver":"","Repesado":"","Anezo":"","Btl":"1599","Pitcher(1.5 Lit)":"","Bar Man Special":"No"},{"Category":"Red Wine","Item Name":"Fratell Cabernet Shiraz","Description":"","Mocktail":"","30Ml":"","330Ml":"","275Ml":"","Glass":"349","Silver":"","Repesado":"","Anezo":"","Btl":"1599","Pitcher(1.5 Lit)":"","Bar Man Special":"No"},{"Category":"White Wine","Item Name":"Jacob Creak Chordonnay","Description":"","Mocktail":"","30Ml":"","330Ml":"","275Ml":"","Glass":"","Silver":"","Repesado":"","Anezo":"","Btl":"2599","Pitcher(1.5 Lit)":"","Bar Man Special":"No"},{"Category":"White Wine","Item Name":"Sula Chenin Blanc","Description":"","Mocktail":"","30Ml":"","330Ml":"","275Ml":"","Glass":"349","Silver":"","Repesado":"","Anezo":"","Btl":"1599","Pitcher(1.5 Lit)":"","Bar Man Special":"No"},{"Category":"White Wine","Item Name":"Sula  Sauvignon Blanc","Description":"","Mocktail":"","30Ml":"","330Ml":"","275Ml":"","Glass":"349","Silver":"","Repesado":"","Anezo":"","Btl":"1599","Pitcher(1.5 Lit)":"","Bar Man Special":"No"},{"Category":"White Wine","Item Name":"Fratelli Chenin Blane","Description":"","Mocktail":"","30Ml":"","330Ml":"","275Ml":"","Glass":"349","Silver":"","Repesado":"","Anezo":"","Btl":"1599","Pitcher(1.5 Lit)":"","Bar Man Special":"No"},{"Category":"White Wine","Item Name":"Fratelli Chardonnay","Description":"","Mocktail":"","30Ml":"","330Ml":"","275Ml":"","Glass":"349","Silver":"","Repesado":"","Anezo":"","Btl":"1599","Pitcher(1.5 Lit)":"","Bar Man Special":"No"},{"Category":"Rose Wine","Item Name":"Sula Zinfandel Rose","Description":"","Mocktail":"","30Ml":"","330Ml":"","275Ml":"","Glass":"349","Silver":"","Repesado":"","Anezo":"","Btl":"1599","Pitcher(1.5 Lit)":"","Bar Man Special":"No"},{"Category":"Rose Wine","Item Name":"Rose","Description":"","Mocktail":"","30Ml":"","330Ml":"","275Ml":"","Glass":"349","Silver":"","Repesado":"","Anezo":"","Btl":"1499","Pitcher(1.5 Lit)":"","Bar Man Special":"No"},{"Category":"Dessert  Wine","Item Name":"Sula Late Harvest ","Description":"","Mocktail":"","30Ml":"","330Ml":"","275Ml":"","Glass":"439","Silver":"","Repesado":"","Anezo":"","Btl":"2199","Pitcher(1.5 Lit)":"","Bar Man Special":"No"},{"Category":"","Item Name":"","Description":"** Standard Mesure 30Ml","Mocktail":"","30Ml":"","330Ml":"","275Ml":"","Glass":"","Silver":"","Repesado":"","Anezo":"","Btl":"","Pitcher(1.5 Lit)":"","Bar Man Special":""},{"Category":"","Item Name":"","Description":"** We Levy Service Charges Of Only 7%","Mocktail":"","30Ml":"","330Ml":"","275Ml":"","Glass":"","Silver":"","Repesado":"","Anezo":"","Btl":"","Pitcher(1.5 Lit)":"","Bar Man Special":""},{"Category":"","Item Name":"","Description":"** Government Taxes Extra","Mocktail":"","30Ml":"","330Ml":"","275Ml":"","Glass":"","Silver":"","Repesado":"","Anezo":"","Btl":"","Pitcher(1.5 Lit)":"","Bar Man Special":""}],"rowCount":164,"fetchedAt":"2026-04-14T11:29:44.480Z"}